make_lambda_package/__init__.py
make_lambda_package/archive.py
make_lambda_package/cli.py
make_lambda_package/deps.py
make_lambda_package/fsutil.py
make_lambda_package/scm.py
make_lambda_package-1.1.0.dist-info/LICENSE
make_lambda_package-1.1.0.dist-info/METADATA
make_lambda_package-1.1.0.dist-info/WHEEL
make_lambda_package-1.1.0.dist-info/entry_points.txt
make_lambda_package-1.1.0.dist-info/top_level.txt
make_lambda_package-1.1.0.dist-info/RECORD
