Metadata-Version: 2.1
Name: make-lambda-package
Version: 1.1.0
Summary: Bundle up deployment packages for AWS Lambda.
Home-page: https://github.com/NoRedInk/make-lambda-package
Author: Marica Odagaki
Author-email: marica@noredink.com
License: BSD-3-Clause
Platform: any
Classifier: Development Status :: 4 - Beta
Classifier: Environment :: Console
Classifier: Intended Audience :: Developers
Classifier: License :: OSI Approved :: BSD License
Classifier: Programming Language :: Python
Classifier: Programming Language :: Python :: 3
Classifier: Topic :: System :: Software Distribution
Requires-Dist: click
Requires-Dist: pip
Requires-Dist: six
